main.py
poetry2uv-0.1.2.dist-info/METADATA
poetry2uv-0.1.2.dist-info/WHEEL
poetry2uv-0.1.2.dist-info/entry_points.txt
poetry2uv-0.1.2.dist-info/top_level.txt
poetry2uv-0.1.2.dist-info/RECORD
