Metadata-Version: 2.1
Name: poetry2uv
Version: 0.1.2
Summary: Convert Poetry pyproject.toml to UV pyproject.toml
Project-URL: source, https://github.com/OhMyMndy/poetry2uv
Requires-Python: >=3.11
Requires-Dist: poetry>=1.8.5
Requires-Dist: toml>=0.10.2
